jfits/__init__.py
jfits/jfits.py
jfits-1.0.0.dist-info/licenses/LICENSE
jfits-1.0.0.dist-info/METADATA
jfits-1.0.0.dist-info/WHEEL
jfits-1.0.0.dist-info/top_level.txt
jfits-1.0.0.dist-info/RECORD
