Metadata-Version: 2.4
Name: jfits
Version: 1.0.0
Summary: Interactive numpy array and FITS image viewer with WCS support and centroiding
Author-email: Jordan Stone <3971752+jordan-stone@users.noreply.github.com>
License: MIT
Project-URL: Homepage, https://github.com/jordan-stone/jfits
Project-URL: Repository, https://github.com/jordan-stone/jfits
Project-URL: Issues, https://github.com/jordan-stone/jfits/issues
Keywords: astronomy,fits,visualization,wcs,centroiding
Classifier: Development Status :: 4 - Beta
Classifier: Intended Audience :: Science/Research
Classifier: License :: OSI Approved :: MIT License
Classifier: Programming Language :: Python :: 3
Classifier: Programming Language :: Python :: 3.8
Classifier: Programming Language :: Python :: 3.9
Classifier: Programming Language :: Python :: 3.10
Classifier: Programming Language :: Python :: 3.11
Classifier: Programming Language :: Python :: 3.12
Classifier: Topic :: Scientific/Engineering :: Astronomy
Requires-Python: >=3.8
License-File: LICENSE
Requires-Dist: numpy>=1.20.0
Requires-Dist: matplotlib>=3.3.0
Requires-Dist: astropy>=4.0
Requires-Dist: scipy>=1.7.0
Provides-Extra: dev
Requires-Dist: pytest>=7.0; extra == "dev"
Requires-Dist: pytest-cov>=3.0; extra == "dev"
Dynamic: license-file
